siotelegram/__init__.py
siotelegram/protocol.py
siotelegram/io/__init__.py
siotelegram/io/io_aiohttp.py
siotelegram/io/io_httpx.py
siotelegram/io/io_requests.py
siotelegram-1.3.0.dist-info/METADATA
siotelegram-1.3.0.dist-info/WHEEL
siotelegram-1.3.0.dist-info/top_level.txt
siotelegram-1.3.0.dist-info/RECORD
