Metadata-Version: 2.1
Name: siotelegram
Version: 1.3.0
Summary: Sans io telegram api with couple io backends
Home-page: https://github.com/pohmelie/siotelegram
Author: pohmelie
Author-email: multisosnooley@gmail.com
License: WTFPL
Platform: UNKNOWN
Classifier: Programming Language :: Python
Classifier: Programming Language :: Python :: 3
Requires-Python: >= 3.7
Provides-Extra: aiohttp
Requires-Dist: aiohttp ; extra == 'aiohttp'
Requires-Dist: async-timeout (>=1.2.0) ; extra == 'aiohttp'
Provides-Extra: httpx
Requires-Dist: httpx ; extra == 'httpx'
Requires-Dist: async-timeout ; extra == 'httpx'
Provides-Extra: requests
Requires-Dist: requests ; extra == 'requests'
